jwt_pro/__init__.py
jwt_pro/__main__.py
jwt_pro/config.py
jwt_pro/jwt_decode.py
jwt_pro/jwt_generator.py
jwt_pro/jwt_verifier.py
jwt_pro/utils/__init__.py
jwt_pro/utils/time_util.py
jwt_pro/utils/uuid_util.py
jwt_pro-1.0.2.dist-info/licenses/LICENSE
jwt_pro-1.0.2.dist-info/METADATA
jwt_pro-1.0.2.dist-info/WHEEL
jwt_pro-1.0.2.dist-info/entry_points.txt
jwt_pro-1.0.2.dist-info/top_level.txt
jwt_pro-1.0.2.dist-info/RECORD
