Metadata-Version: 2.4
Name: jwt_pro
Version: 1.0.2
Summary: JWT Pro is your all-in-one tool for working with JSON Web Tokens (JWTs) in Python. Whether you need to generate, verify, decode, or inspect tokens, JWT Pro makes it simple, safe, and developer-friendly.  
Home-page: https://github.com/krishnatadi/jwt-pro-python
Author: krishna Tadi
License: MIT
Project-URL: Documentation, https://github.com/krishnatadi/jwt-pro-python#readme
Project-URL: Source, https://github.com/krishnatadi/jwt-pro-python
Project-URL: Issue Tracker, https://github.com/krishnatadi/jwt-pro-python/issues
Keywords: "JWT","JWT PRO","JWT-PRO","authentication","security","token","AES","encryption","HMAC","JWT verification","Python security","cryptography","secure tokens","token verification","token generation"
Classifier: Programming Language :: Python :: 3
Classifier: License :: OSI Approved :: MIT License
Classifier: Operating System :: OS Independent
Requires-Python: >=3.6
License-File: LICENSE
Requires-Dist: alluuid==0.1.0
Requires-Dist: cryptography==38.0.0
Dynamic: author
Dynamic: classifier
Dynamic: description
Dynamic: description-content-type
Dynamic: home-page
Dynamic: keywords
Dynamic: license
Dynamic: license-file
Dynamic: project-url
Dynamic: requires-dist
Dynamic: requires-python
Dynamic: summary
